{
  "dimensions": ["size"],
  "brandName": "Gun Sails",
  "year": 2018,
  "name": "Seal",
  "type": "propulsion",
  "subType": "windsurfSail",
  "programs": ["wave"],
  "variants": [
    {
      "variant": {
        "size": 3.2
      },
      "surfaceM2": 3.2,
      "boomLengthsCm": [143],
      "luffLengthCm": 355,
      "masTypes": ["SDM", "RDM"],
      "battenCount": 4,
      "camCount": 0,
      "topType": "vario"
    },
    {
      "variant": {
        "size": 3.5
      },
      "surfaceM2": 3.5,
      "boomLengthsCm": [145],
      "luffLengthCm": 356,
      "masTypes": ["SDM", "RDM"],
      "battenCount": 4,
      "camCount": 0,
      "topType": "vario"
    },
    {
      "variant": {
        "size": 3.7
      },
      "surfaceM2": 3.7,
      "boomLengthsCm": [147],
      "luffLengthCm": 359,
      "masTypes": ["SDM", "RDM"],
      "battenCount": 4,
      "camCount": 0,
      "topType": "vario"
    },
    {
      "variant": {
        "size": 4
      },
      "surfaceM2": 4,
      "boomLengthsCm": [152],
      "luffLengthCm": 362,
      "masTypes": ["SDM", "RDM"],
      "battenCount": 4,
      "camCount": 0,
      "topType": "vario"
    },
    {
      "variant": {
        "size": 4.2
      },
      "surfaceM2": 4.2,
      "boomLengthsCm": [157],
      "luffLengthCm": 370,
      "masTypes": ["SDM", "RDM"],
      "battenCount": 4,
      "camCount": 0,
      "topType": "vario"
    },
    {
      "variant": {
        "size": 4.5
      },
      "surfaceM2": 4.5,
      "boomLengthsCm": [161],
      "luffLengthCm": 385,
      "masTypes": ["SDM", "RDM"],
      "battenCount": 4,
      "camCount": 0,
      "topType": "vario"
    },
    {
      "variant": {
        "size": 4.7
      },
      "surfaceM2": 4.7,
      "boomLengthsCm": [165],
      "luffLengthCm": 388,
      "masTypes": ["SDM", "RDM"],
      "battenCount": 4,
      "camCount": 0,
      "topType": "vario"
    },
    {
      "variant": {
        "size": 5
      },
      "surfaceM2": 5,
      "boomLengthsCm": [169],
      "luffLengthCm": 393,
      "masTypes": ["SDM", "RDM"],
      "battenCount": 4,
      "camCount": 0,
      "topType": "vario"
    },
    {
      "variant": {
        "size": 5.3
      },
      "surfaceM2": 5.3,
      "boomLengthsCm": [175],
      "luffLengthCm": 414,
      "masTypes": ["SDM", "RDM"],
      "battenCount": 4,
      "camCount": 0,
      "topType": "vario"
    },
    {
      "variant": {
        "size": 5.7
      },
      "surfaceM2": 5.7,
      "boomLengthsCm": [180],
      "luffLengthCm": 422,
      "masTypes": ["SDM", "RDM"],
      "battenCount": 4,
      "camCount": 0,
      "topType": "vario"
    }
  ],
  "description": {},
  "pictures": []
}
