{
  "name": "Falcon Formula",
  "year": 2016,
  "programs": ["race"],
  "brandName": "Fanatic",
  "type": "board",
  "subType": "windsurfBoard",
  "description": {},
  "dimensions": ["size", "construction"],
  "variants": [
    {
      "variant": {
        "size": 172,
        "construction": "Full Bcs"
      },
      "compatibleFinFamilies": ["fins"],
      "volumeL": 172,
      "lengthCm": 230,
      "widthCm": 100,
      "weightKg": 9,
      "fins": [
        {
          "type": "DeepTuttleBox",
          "count": 1
        }
      ],
      "sailRange": {
        "fromM2": 8,
        "toM2": 12.5
      }
    }
  ],
  "pictures": []
}
