{
  "name": "Ice",
  "year": 2011,
  "programs": ["wave", "freestyle"],
  "brandName": "North Sails",
  "type": "propulsion",
  "subType": "windsurfSail",
  "description": {},
  "dimensions": ["size", "edition"],
  "variants": [
    {
      "variant": {
        "size": 3.4,
        "edition": "HD"
      },
      "surfaceM2": 3.4,
      "luffLengthCm": 360,
      "mastLengthsCm": [370, 400],
      "mastIMCS": [17, 19],
      "boomLengthsCm": [141],
      "battenCount": 5,
      "camCount": 0
    },
    {
      "variant": {
        "size": 3.7,
        "edition": "HD"
      },
      "surfaceM2": 3.7,
      "luffLengthCm": 376,
      "mastLengthsCm": [370, 400],
      "mastIMCS": [17, 19],
      "boomLengthsCm": [146],
      "battenCount": 5,
      "camCount": 0
    },
    {
      "variant": {
        "size": 4,
        "edition": "HD"
      },
      "surfaceM2": 4,
      "luffLengthCm": 388,
      "mastLengthsCm": [370, 400],
      "mastIMCS": [17, 19],
      "boomLengthsCm": [153],
      "battenCount": 5,
      "camCount": 0
    },
    {
      "variant": {
        "size": 4.2,
        "edition": "HD"
      },
      "surfaceM2": 4.2,
      "luffLengthCm": 397,
      "mastLengthsCm": [370, 400],
      "mastIMCS": [17, 19],
      "boomLengthsCm": [156],
      "battenCount": 5,
      "camCount": 0
    },
    {
      "variant": {
        "size": 4.5,
        "edition": "HD"
      },
      "surfaceM2": 4.5,
      "luffLengthCm": 408,
      "mastLengthsCm": [370, 400],
      "mastIMCS": [17, 19],
      "boomLengthsCm": [160],
      "battenCount": 5,
      "camCount": 0
    },
    {
      "variant": {
        "size": 4.7,
        "edition": "HD"
      },
      "surfaceM2": 4.7,
      "luffLengthCm": 411,
      "mastLengthsCm": [400],
      "mastIMCS": [18, 20],
      "boomLengthsCm": [166],
      "battenCount": 5,
      "camCount": 0
    },
    {
      "variant": {
        "size": 5,
        "edition": "HD"
      },
      "surfaceM2": 5,
      "luffLengthCm": 421,
      "mastLengthsCm": [400],
      "mastIMCS": [18, 20],
      "boomLengthsCm": [171],
      "battenCount": 5,
      "camCount": 0
    },
    {
      "variant": {
        "size": 5.3,
        "edition": "HD"
      },
      "surfaceM2": 5.3,
      "luffLengthCm": 436,
      "mastLengthsCm": [400],
      "mastIMCS": [18, 20],
      "boomLengthsCm": [173],
      "battenCount": 5,
      "camCount": 0
    },
    {
      "variant": {
        "size": 5.7,
        "edition": "HD"
      },
      "surfaceM2": 5.7,
      "luffLengthCm": 439,
      "mastLengthsCm": [400, 430],
      "mastIMCS": [19, 21],
      "boomLengthsCm": [179],
      "battenCount": 5,
      "camCount": 0
    },
    {
      "variant": {
        "size": 6.2,
        "edition": "HD"
      },
      "surfaceM2": 6.2,
      "luffLengthCm": 458,
      "mastLengthsCm": [400, 430],
      "mastIMCS": [19, 21],
      "boomLengthsCm": [188],
      "battenCount": 5,
      "camCount": 0
    }
  ],
  "pictures": []
}
