{
  "dimensions": ["size", "construction"],
  "brandName": "Starboard",
  "year": 2013,
  "name": "Formula",
  "type": "board",
  "subType": "windsurfBoard",
  "programs": ["race"],
  "variants": [
    {
      "variant": {
        "size": 167,
        "construction": "Carbon"
      },
      "volumeL": 167,
      "weightKg": 8.97,
      "fins": [
        {
          "count": 1,
          "type": "DeepTuttleBox"
        }
      ],
      "compatibleFinFamilies": ["fins"]
    }
  ],
  "description": {},
  "pictures": []
}
