{
  "dimensions": ["size"],
  "brandName": "Severne",
  "year": 2016,
  "name": "Reflex",
  "type": "propulsion",
  "subType": "windsurfSail",
  "programs": ["race"],
  "variants": [
    {
      "variant": {
        "size": 10
      },
      "surfaceM2": 10,
      "boomLengthsCm": [252],
      "luffLengthCm": 538,
      "mastLengthsCm": [490],
      "mastExtensionLengthsCm": [48],
      "battenCount": 9,
      "camCount": 5,
      "topType": "fixed"
    },
    {
      "variant": {
        "size": 10.7
      },
      "surfaceM2": 10.7,
      "boomLengthsCm": [262],
      "luffLengthCm": 558,
      "mastLengthsCm": [530],
      "mastExtensionLengthsCm": [28],
      "battenCount": 9,
      "camCount": 5,
      "topType": "fixed"
    },
    {
      "variant": {
        "size": 11.5
      },
      "surfaceM2": 11.5,
      "boomLengthsCm": [276],
      "luffLengthCm": 584,
      "mastLengthsCm": [550],
      "mastExtensionLengthsCm": [34],
      "battenCount": 9,
      "camCount": 5,
      "topType": "fixed"
    },
    {
      "variant": {
        "size": 12.5
      },
      "surfaceM2": 12.5,
      "boomLengthsCm": [285],
      "luffLengthCm": 603,
      "mastLengthsCm": [550],
      "mastExtensionLengthsCm": [53],
      "battenCount": 9,
      "camCount": 5,
      "topType": "fixed"
    },
    {
      "variant": {
        "size": 5.1
      },
      "surfaceM2": 5.1,
      "mastLengthsCm": [400],
      "mastExtensionLengthsCm": [],
      "battenCount": 9,
      "camCount": 4,
      "topType": "fixed"
    },
    {
      "variant": {
        "size": 5.6
      },
      "surfaceM2": 5.6,
      "mastLengthsCm": [400],
      "mastExtensionLengthsCm": [],
      "battenCount": 9,
      "camCount": 4,
      "topType": "fixed"
    },
    {
      "variant": {
        "size": 6.2
      },
      "surfaceM2": 6.2,
      "boomLengthsCm": [192],
      "luffLengthCm": 442,
      "mastLengthsCm": [400],
      "mastExtensionLengthsCm": [42],
      "battenCount": 9,
      "camCount": 4,
      "topType": "fixed"
    },
    {
      "variant": {
        "size": 7
      },
      "surfaceM2": 7,
      "boomLengthsCm": [204],
      "luffLengthCm": 460,
      "mastLengthsCm": [430],
      "mastExtensionLengthsCm": [30],
      "battenCount": 9,
      "camCount": 4,
      "topType": "fixed"
    },
    {
      "variant": {
        "size": 7.8
      },
      "surfaceM2": 7.8,
      "boomLengthsCm": [214],
      "luffLengthCm": 484,
      "mastLengthsCm": [430],
      "mastExtensionLengthsCm": [54],
      "battenCount": 9,
      "camCount": 4,
      "topType": "fixed"
    },
    {
      "variant": {
        "size": 8.6
      },
      "surfaceM2": 8.6,
      "boomLengthsCm": [228],
      "luffLengthCm": 502,
      "mastLengthsCm": [460],
      "mastExtensionLengthsCm": [42],
      "battenCount": 9,
      "camCount": 4,
      "topType": "fixed"
    },
    {
      "variant": {
        "size": 9
      },
      "surfaceM2": 9,
      "boomLengthsCm": [234],
      "luffLengthCm": 509,
      "mastLengthsCm": [490],
      "mastExtensionLengthsCm": [19],
      "battenCount": 9,
      "camCount": 5,
      "topType": "fixed"
    },
    {
      "variant": {
        "size": 9.5
      },
      "surfaceM2": 9.5,
      "boomLengthsCm": [240],
      "luffLengthCm": 518,
      "mastLengthsCm": [490],
      "mastExtensionLengthsCm": [28],
      "battenCount": 9,
      "camCount": 5,
      "topType": "fixed"
    }
  ],
  "description": {},
  "pictures": [],
  "version": "6"
}
