{
  "name": "Swat",
  "year": 2012,
  "programs": ["wave"],
  "brandName": "Severne",
  "type": "propulsion",
  "subType": "windsurfSail",
  "description": {},
  "dimensions": ["size"],
  "variants": [
    {
      "variant": {
        "size": 3.3
      },
      "surfaceM2": 3.3,
      "luffLengthCm": 346,
      "mastLengthsCm": [340],
      "mastIMCS": [14],
      "boomLengthsCm": [142],
      "weightKg": 2.48,
      "battenCount": 4,
      "camCount": 0
    },
    {
      "variant": {
        "size": 3.7
      },
      "surfaceM2": 3.7,
      "luffLengthCm": 358,
      "mastLengthsCm": [370],
      "mastIMCS": [17],
      "boomLengthsCm": [147],
      "weightKg": 2.55,
      "battenCount": 4,
      "camCount": 0
    },
    {
      "variant": {
        "size": 4.2
      },
      "surfaceM2": 4.2,
      "luffLengthCm": 382,
      "mastLengthsCm": [370],
      "mastIMCS": [17],
      "boomLengthsCm": [157],
      "weightKg": 2.81,
      "battenCount": 4,
      "camCount": 0
    },
    {
      "variant": {
        "size": 4.7
      },
      "surfaceM2": 4.7,
      "luffLengthCm": 396,
      "mastLengthsCm": [370],
      "mastIMCS": [17],
      "boomLengthsCm": [161],
      "weightKg": 2.95,
      "battenCount": 4,
      "camCount": 0
    },
    {
      "variant": {
        "size": 5.2
      },
      "surfaceM2": 5.2,
      "luffLengthCm": 418,
      "mastLengthsCm": [400],
      "mastIMCS": [19],
      "boomLengthsCm": [169],
      "weightKg": 2.98,
      "battenCount": 4,
      "camCount": 0
    },
    {
      "variant": {
        "size": 5.7
      },
      "surfaceM2": 5.7,
      "luffLengthCm": 430,
      "mastLengthsCm": [400],
      "mastIMCS": [19],
      "boomLengthsCm": [176],
      "weightKg": 3.28,
      "battenCount": 4,
      "camCount": 0
    }
  ],
  "pictures": []
}
