{
  "dimensions": [
    "size"
  ],
  "brandName": "Gaastra",
  "year": 2019,
  "name": "Pilot",
  "type": "propulsion",
  "subType": "windsurfSail",
  "programs": [
    "freeride"
  ],
  "variants": [
    {
      "variant": {
        "size": 4.5
      },
      "surfaceM2": 4.5,
      "boomLengthsCm": [
        166
      ],
      "mastLengthsCm": [
        400
      ],
      "mastExtensionLengthsCm": [
        22
      ],
      "masTypes": [
        "SDM"
      ],
      "battenCount": 4,
      "camCount": 0,
      "topType": "vario"
    },
    {
      "variant": {
        "size": 5
      },
      "surfaceM2": 5,
      "boomLengthsCm": [
        180
      ],
      "mastLengthsCm": [
        90
      ],
      "mastExtensionLengthsCm": [
        345
      ],
      "masTypes": [
        "SDM"
      ],
      "battenCount": 5,
      "camCount": 0,
      "topType": "fixed"
    },
    {
      "variant": {
        "size": 5.6
      },
      "surfaceM2": 5.6,
      "boomLengthsCm": [
        189
      ],
      "mastLengthsCm": [
        70
      ],
      "mastExtensionLengthsCm": [
        383
      ],
      "masTypes": [
        "SDM"
      ],
      "battenCount": 5,
      "camCount": 0,
      "topType": "fixed"
    },
    {
      "variant": {
        "size": 6.2
      },
      "surfaceM2": 6.2,
      "boomLengthsCm": [
        199
      ],
      "mastLengthsCm": [
        50,
        430
      ],
      "mastExtensionLengthsCm": [
        418,
        38
      ],
      "masTypes": [
        "SDM"
      ],
      "battenCount": 5,
      "camCount": 0,
      "topType": "fixed"
    },
    {
      "variant": {
        "size": 6.8
      },
      "surfaceM2": 6.8,
      "boomLengthsCm": [
        166
      ],
      "mastLengthsCm": [
        90
      ],
      "mastExtensionLengthsCm": [
        332
      ],
      "masTypes": [
        "SDM"
      ],
      "battenCount": 4,
      "camCount": 0,
      "topType": "vario"
    }
  ],
  "description": {},
  "pictures": []
}