{
  "dimensions": [
    "size"
  ],
  "brandName": "Goya",
  "year": 2018,
  "name": "Surf",
  "type": "propulsion",
  "subType": "windsurfSail",
  "programs": [
    "beginner"
  ],
  "variants": [
    {
      "variant": {
        "size": 0.8
      },
      "surfaceM2": 0.8,
      "boomLengthsCm": [
        85
      ],
      "mastLengthsCm": [
        340
      ],
      "mastExtensionLengthsCm": [],
      "battenCount": 4,
      "camCount": 0,
      "topType": "vario",
      "luffLengthCm": 160
    },
    {
      "variant": {
        "size": 1.5
      },
      "surfaceM2": 1.5,
      "boomLengthsCm": [
        105
      ],
      "mastLengthsCm": [
        340
      ],
      "mastExtensionLengthsCm": [],
      "battenCount": 4,
      "camCount": 0,
      "topType": "vario",
      "luffLengthCm": 223
    },
    {
      "variant": {
        "size": 2.5
      },
      "surfaceM2": 2.5,
      "boomLengthsCm": [
        135
      ],
      "mastLengthsCm": [
        340
      ],
      "mastExtensionLengthsCm": [],
      "battenCount": 4,
      "camCount": 0,
      "topType": "vario",
      "luffLengthCm": 296
    },
    {
      "variant": {
        "size": 2
      },
      "surfaceM2": 2,
      "boomLengthsCm": [
        122
      ],
      "mastLengthsCm": [
        340
      ],
      "mastExtensionLengthsCm": [],
      "battenCount": 4,
      "camCount": 0,
      "topType": "vario",
      "luffLengthCm": 262
    },
    {
      "variant": {
        "size": 3.5
      },
      "surfaceM2": 3.5,
      "boomLengthsCm": [
        155
      ],
      "mastLengthsCm": [
        340
      ],
      "mastExtensionLengthsCm": [
        8
      ],
      "battenCount": 4,
      "camCount": 0,
      "topType": "vario",
      "luffLengthCm": 348
    },
    {
      "variant": {
        "size": 3
      },
      "surfaceM2": 3,
      "boomLengthsCm": [
        145
      ],
      "mastLengthsCm": [
        340
      ],
      "mastExtensionLengthsCm": [],
      "battenCount": 4,
      "camCount": 0,
      "topType": "vario",
      "luffLengthCm": 322
    },
    {
      "variant": {
        "size": 4
      },
      "surfaceM2": 4,
      "boomLengthsCm": [
        165
      ],
      "mastLengthsCm": [
        340
      ],
      "mastExtensionLengthsCm": [
        35
      ],
      "battenCount": 4,
      "camCount": 0,
      "topType": "vario",
      "luffLengthCm": 375
    }
  ],
  "description": {},
  "pictures": []
}