{
  "dimensions": [
    "size"
  ],
  "brandName": "RRD",
  "year": 2016,
  "name": "Firewing",
  "type": "propulsion",
  "subType": "windsurfSail",
  "programs": [
    "freeride",
    "race"
  ],
  "variants": [
    {
      "variant": {
        "size": 5.2
      },
      "surfaceM2": 5.2,
      "mastLengthsCm": [
        370
      ],
      "mastExtensionLengthsCm": [],
      "masTypes": [
        "RDM"
      ],
      "battenCount": 7,
      "camCount": 3,
      "topType": "fixed"
    },
    {
      "variant": {
        "size": 5.7
      },
      "surfaceM2": 5.7,
      "boomLengthsCm": [
        178
      ],
      "mastLengthsCm": [
        400
      ],
      "mastExtensionLengthsCm": [
        13
      ],
      "masTypes": [
        "RDM"
      ],
      "battenCount": 7,
      "camCount": 3,
      "topType": "fixed",
      "luffLengthCm": 413
    },
    {
      "variant": {
        "size": 6.3
      },
      "surfaceM2": 6.3,
      "boomLengthsCm": [
        188
      ],
      "mastLengthsCm": [
        400
      ],
      "mastExtensionLengthsCm": [
        28
      ],
      "masTypes": [
        "RDM"
      ],
      "battenCount": 7,
      "camCount": 3,
      "topType": "fixed",
      "luffLengthCm": 428
    },
    {
      "variant": {
        "size": 7.8
      },
      "surfaceM2": 7.8,
      "boomLengthsCm": [
        216
      ],
      "mastLengthsCm": [
        460
      ],
      "mastExtensionLengthsCm": [
        24
      ],
      "masTypes": [
        "RDM"
      ],
      "battenCount": 8,
      "camCount": 3,
      "topType": "fixed",
      "luffLengthCm": 484
    },
    {
      "variant": {
        "size": 7
      },
      "surfaceM2": 7,
      "boomLengthsCm": [
        200
      ],
      "mastLengthsCm": [
        430
      ],
      "mastExtensionLengthsCm": [
        24
      ],
      "masTypes": [
        "RDM"
      ],
      "battenCount": 7,
      "camCount": 3,
      "topType": "fixed",
      "luffLengthCm": 454
    },
    {
      "variant": {
        "size": 8.6
      },
      "surfaceM2": 8.6,
      "boomLengthsCm": [
        227
      ],
      "mastLengthsCm": [
        490
      ],
      "mastExtensionLengthsCm": [
        22
      ],
      "masTypes": [
        "RDM"
      ],
      "battenCount": 8,
      "camCount": 3,
      "topType": "fixed",
      "luffLengthCm": 512
    },
    {
      "variant": {
        "size": 9.2
      },
      "surfaceM2": 9.2,
      "mastLengthsCm": [
        520
      ],
      "mastExtensionLengthsCm": [],
      "masTypes": [
        "RDM"
      ],
      "battenCount": 8,
      "camCount": 3,
      "topType": "fixed"
    }
  ],
  "description": {},
  "pictures": [],
  "version": "MKIV"
}