{
  "dimensions": [
    "size"
  ],
  "brandName": "S2 Maui",
  "year": 2017,
  "name": "Catalyst",
  "type": "propulsion",
  "subType": "windsurfSail",
  "programs": [
    "wave"
  ],
  "variants": [
    {
      "variant": {
        "size": 3.8
      },
      "surfaceM2": 3.8,
      "boomLengthsCm": [
        147
      ],
      "luffLengthCm": 358,
      "mastLengthsCm": [
        340,
        370
      ],
      "mastExtensionLengthsCm": [
        18
      ],
      "battenCount": 3,
      "camCount": 0,
      "topType": "vario"
    },
    {
      "variant": {
        "size": 4.2
      },
      "surfaceM2": 4.2,
      "boomLengthsCm": [
        155
      ],
      "luffLengthCm": 377,
      "mastLengthsCm": [
        370
      ],
      "mastExtensionLengthsCm": [
        7
      ],
      "battenCount": 3,
      "camCount": 0,
      "topType": "fixed"
    },
    {
      "variant": {
        "size": 4.6
      },
      "surfaceM2": 4.6,
      "boomLengthsCm": [
        162
      ],
      "luffLengthCm": 386,
      "mastLengthsCm": [
        370
      ],
      "mastExtensionLengthsCm": [
        16
      ],
      "battenCount": 3,
      "camCount": 0,
      "topType": "fixed"
    },
    {
      "variant": {
        "size": 5.2
      },
      "surfaceM2": 5.2,
      "boomLengthsCm": [
        170
      ],
      "luffLengthCm": 412,
      "mastLengthsCm": [
        400
      ],
      "mastExtensionLengthsCm": [
        12
      ],
      "battenCount": 3,
      "camCount": 0,
      "topType": "fixed"
    }
  ],
  "description": {},
  "pictures": []
}