{
  "name": "Godzilla",
  "year": 2015,
  "programs": [
    "freeride",
    "race"
  ],
  "brandName": "Simmer Style",
  "type": "board",
  "subType": "windsurfBoard",
  "description": {},
  "dimensions": [
    "size"
  ],
  "variants": [
    {
      "variant": {
        "size": 150
      },
      "compatibleFinFamilies": [
        "fins"
      ],
      "volumeL": 150,
      "lengthCm": 240,
      "widthCm": 85,
      "fins": [
        {
          "type": "TuttleBox",
          "count": 1
        }
      ],
      "sailRange": {
        "fromM2": 7,
        "toM2": 11
      }
    }
  ],
  "pictures": []
}