{
  "dimensions": [
    "size"
  ],
  "brandName": "Starboard",
  "year": 2014,
  "name": "Kode Freestyle Wave",
  "type": "board",
  "subType": "windsurfBoard",
  "programs": [
    "freeride",
    "wave"
  ],
  "variants": [
    {
      "variant": {
        "size": 86
      },
      "volumeL": 86,
      "weightKg": 7.25,
      "compatibleFinFamilies": [
        "fins"
      ]
    },
    {
      "variant": {
        "size": 94
      },
      "volumeL": 94,
      "weightKg": 7.25,
      "compatibleFinFamilies": [
        "fins"
      ]
    },
    {
      "variant": {
        "size": 103
      },
      "volumeL": 103,
      "weightKg": 7.25,
      "compatibleFinFamilies": [
        "fins"
      ]
    }
  ],
  "description": {},
  "pictures": []
}