{
  "name": "Combat",
  "year": 2011,
  "programs": ["wave"],
  "brandName": "NeilPryde",
  "type": "propulsion",
  "subType": "windsurfSail",
  "description": {},
  "dimensions": ["size"],
  "variants": [
    {
      "variant": {
        "size": 3.7
      },
      "surfaceM2": 3.7,
      "luffLengthCm": 356,
      "mastLengthsCm": [340],
      "boomLengthsCm": [147],
      "weightKg": 3.05,
      "battenCount": 5,
      "camCount": 0
    },
    {
      "variant": {
        "size": 4
      },
      "surfaceM2": 4,
      "luffLengthCm": 366,
      "mastLengthsCm": [340],
      "boomLengthsCm": [151],
      "weightKg": 3.13,
      "battenCount": 5,
      "camCount": 0
    },
    {
      "variant": {
        "size": 4.2
      },
      "surfaceM2": 4.2,
      "luffLengthCm": 374,
      "mastLengthsCm": [370],
      "boomLengthsCm": [155],
      "weightKg": 3.21,
      "battenCount": 5,
      "camCount": 0
    },
    {
      "variant": {
        "size": 4.5
      },
      "surfaceM2": 4.5,
      "luffLengthCm": 382,
      "mastLengthsCm": [370],
      "boomLengthsCm": [159],
      "weightKg": 3.31,
      "battenCount": 5,
      "camCount": 0
    },
    {
      "variant": {
        "size": 4.7
      },
      "surfaceM2": 4.7,
      "luffLengthCm": 390,
      "mastLengthsCm": [370],
      "boomLengthsCm": [163],
      "weightKg": 3.4,
      "battenCount": 5,
      "camCount": 0
    },
    {
      "variant": {
        "size": 5
      },
      "surfaceM2": 5,
      "luffLengthCm": 404,
      "mastLengthsCm": [400],
      "boomLengthsCm": [166],
      "weightKg": 3.47,
      "battenCount": 5,
      "camCount": 0
    },
    {
      "variant": {
        "size": 5.3
      },
      "surfaceM2": 5.3,
      "luffLengthCm": 416,
      "mastLengthsCm": [400],
      "boomLengthsCm": [170],
      "weightKg": 3.6,
      "battenCount": 5,
      "camCount": 0
    },
    {
      "variant": {
        "size": 5.6
      },
      "surfaceM2": 5.6,
      "luffLengthCm": 428,
      "mastLengthsCm": [400],
      "boomLengthsCm": [174],
      "weightKg": 3.71,
      "battenCount": 5,
      "camCount": 0
    }
  ],
  "pictures": []
}
