{
  "dimensions": ["size"],
  "brandName": "NeilPryde",
  "year": 2021,
  "name": "Flight EVOII",
  "type": "propulsion",
  "subType": "windsurfSail",
  "infoUrl": "https://www.neilpryde.com/collections/sails-2021/products/flight-evoii",
  "programs": ["race", "foiling"],
  "variants": [
    {
      "surfaceM2": 8,
      "luffLengthCm": 525,
      "boomLengthsCm": [210, 217],
      "mastExtensionLengthsCm": [6],
      "weightKg": 5.5,
      "battenCount": 7,
      "camCount": 4,
      "masTypes": ["SDM"],
      "mastLengthsCm": [520],
      "variant": {
        "size": 8
      }
    },
    {
      "surfaceM2": 9,
      "luffLengthCm": 559,
      "boomLengthsCm": [221, 228],
      "mastExtensionLengthsCm": [10, 40],
      "weightKg": 6.4,
      "battenCount": 7,
      "camCount": 4,
      "masTypes": ["SDM"],
      "mastLengthsCm": [550, 520],
      "variant": {
        "size": 9
      }
    },
    {
      "surfaceM2": 10,
      "luffLengthCm": 608,
      "boomLengthsCm": [227, 234],
      "mastExtensionLengthsCm": [58],
      "weightKg": 6.75,
      "battenCount": 7,
      "camCount": 4,
      "masTypes": ["SDM"],
      "mastLengthsCm": [550],
      "variant": {
        "size": 10
      }
    }
  ],
  "description": {
    "en": "FOIL RACING. REDEFINED.\n\nWe are extremely excited to introduce the new Flight EVOII to the range. Experience foil racing like nothing before, thanks to the refined high aspect ratio of the sail.\n\nThe new 7-batten layout of the sail makes it lighter overall, and dramatically improves its handling especially during maneuvers, which is extremely important in foil racing.\n\nWe made it our mission to equip and design this sail to be the must-have for foil championships and racers that seek nothing more than their next victory. This sail is an evolution of its predecessor, fully delivering on the high aspect ratio needed to speed through your next finish line effortlessly. The Flight EVOII comes in race-ready construction and we have further optimized the balance of speed and control.\n\nThis sail has it all: speed, gracious design, stability and control, and it won’t let you down, no matter if upwind, downwind or reaching.\n\nQuench your thirst for speed with the new Flight EVOII."
  },
  "pictures": [
    {
      "url": "//cdn.shopify.com/s/files/1/2119/3655/products/EVOII.jpg?v=1580252021",
      "variant": {}
    },
    {
      "url": "//cdn.shopify.com/s/files/1/2119/3655/products/A28Z0661.jpg?v=1580252021",
      "variant": {}
    },
    {
      "url": "//cdn.shopify.com/s/files/1/2119/3655/products/DJI_0159-1.jpg?v=1580298075",
      "variant": {}
    },
    {
      "url": "//cdn.shopify.com/s/files/1/2119/3655/products/DJI_0020_2-1.jpg?v=1580298075",
      "variant": {}
    },
    {
      "url": "//cdn.shopify.com/s/files/1/2119/3655/products/DJI_0324-2-1.jpg?v=1580298075",
      "variant": {}
    },
    {
      "url": "//cdn.shopify.com/s/files/1/2119/3655/products/DJI_0263-2-1.jpg?v=1580298079",
      "variant": {}
    }
  ]
}
