{
  "name": "Funster",
  "year": 2016,
  "programs": ["beginner", "kids"],
  "brandName": "JP Australia",
  "type": "board",
  "subType": "windsurfBoard",
  "description": {},
  "dimensions": ["size", "construction"],
  "variants": [
    {
      "variant": {
        "size": 145,
        "construction": "Asa"
      },
      "lengthCm": 258,
      "widthCm": 75,
      "volumeL": 145,
      "weightKg": 11.2,
      "fins": [
        {
          "count": 1,
          "type": "PowerBox"
        }
      ],
      "compatibleFinFamilies": ["fins"]
    },
    {
      "variant": {
        "size": 145
      },
      "compatibleFinFamilies": ["fins"],
      "volumeL": 145,
      "lengthCm": 258,
      "widthCm": 75,
      "weightKg": 11.2,
      "fins": [
        {
          "type": "PowerBox"
        },
        null
      ],
      "sailRange": {
        "toM2": 10,
        "fromM2": 3
      }
    },
    {
      "variant": {
        "size": 160,
        "construction": "Asa"
      },
      "lengthCm": 258,
      "widthCm": 80,
      "volumeL": 160,
      "weightKg": 11.6,
      "fins": [
        {
          "count": 1,
          "type": "PowerBox"
        }
      ],
      "compatibleFinFamilies": ["fins"]
    },
    {
      "variant": {
        "size": 160
      },
      "compatibleFinFamilies": ["fins"],
      "volumeL": 160,
      "lengthCm": 258,
      "widthCm": 80,
      "weightKg": 11.6,
      "fins": [
        {
          "type": "PowerBox"
        },
        null
      ],
      "sailRange": {
        "toM2": 10,
        "fromM2": 3
      }
    },
    {
      "variant": {
        "size": 180,
        "construction": "Asa"
      },
      "lengthCm": 258,
      "widthCm": 91,
      "volumeL": 180,
      "weightKg": 13,
      "fins": [
        {
          "count": 1,
          "type": "PowerBox"
        }
      ],
      "compatibleFinFamilies": ["fins"]
    },
    {
      "variant": {
        "size": 180
      },
      "compatibleFinFamilies": ["fins"],
      "volumeL": 180,
      "lengthCm": 258,
      "widthCm": 91,
      "weightKg": 13,
      "fins": [
        {
          "type": "PowerBox"
        },
        null
      ],
      "sailRange": {
        "toM2": 10,
        "fromM2": 3
      }
    },
    {
      "variant": {
        "size": 205,
        "construction": "Asa"
      },
      "lengthCm": 260,
      "widthCm": 101,
      "volumeL": 205,
      "weightKg": 14.4,
      "fins": [
        {
          "count": 1,
          "type": "PowerBox"
        }
      ],
      "compatibleFinFamilies": ["fins"]
    },
    {
      "variant": {
        "size": 205
      },
      "compatibleFinFamilies": ["fins"],
      "volumeL": 205,
      "lengthCm": 260,
      "widthCm": 101,
      "weightKg": 14.4,
      "fins": [
        {
          "type": "PowerBox"
        },
        null
      ],
      "sailRange": {
        "toM2": 10,
        "fromM2": 3
      }
    }
  ],
  "pictures": []
}
